mcschematic/__init__.py
mcschematic/mcschematic.py
mcschematic-11.4.3.dist-info/LICENSE
mcschematic-11.4.3.dist-info/METADATA
mcschematic-11.4.3.dist-info/WHEEL
mcschematic-11.4.3.dist-info/top_level.txt
mcschematic-11.4.3.dist-info/RECORD
