Metadata-Version: 2.1
Name: mcschematic
Version: 11.4.3
Summary: A Minecraft Schematic creator library.
Home-page: https://github.com/Sloimayyy/mcschematic
Author: Sloimay
Author-email: <sloimayyy@gmail.com>
License: Apache License 2.0
Keywords: python,minecraft,schematic
Classifier: Development Status :: 6 - Mature
Classifier: Intended Audience :: Other Audience
Classifier: Programming Language :: Python :: 3.9
Classifier: Programming Language :: Python :: 3.10
Classifier: Operating System :: Unix
Classifier: Operating System :: MacOS :: MacOS X
Classifier: Operating System :: Microsoft :: Windows
License-File: LICENSE
Requires-Dist: nbtlib (>=2.0.4)
Requires-Dist: immutable-views
